setup.py
mozautoeslib/__init__.py
mozautoeslib/eslib.py
mozautoeslib/example.py
mozautoeslib.egg-info/PKG-INFO
mozautoeslib.egg-info/SOURCES.txt
mozautoeslib.egg-info/dependency_links.txt
mozautoeslib.egg-info/not-zip-safe
mozautoeslib.egg-info/requires.txt
mozautoeslib.egg-info/top_level.txt