Metadata-Version: 1.0
Name: mozautoeslib
Version: 0.1.2
Summary: Convenience lib for making certain kinds of ES queries
Home-page: http://hg.mozilla.org/automation/mozautoeslib
Author: Jonathan Griffin
Author-email: jgriffin@mozilla.com
License: MPL
Platform: UNKNOWN
